log_server.py
plugin.py
pytest_single_file_logging-0.1.18.dist-info/DESCRIPTION.rst
pytest_single_file_logging-0.1.18.dist-info/METADATA
pytest_single_file_logging-0.1.18.dist-info/RECORD
pytest_single_file_logging-0.1.18.dist-info/WHEEL
pytest_single_file_logging-0.1.18.dist-info/entry_points.txt
pytest_single_file_logging-0.1.18.dist-info/metadata.json
pytest_single_file_logging-0.1.18.dist-info/top_level.txt
