Metadata-Version: 2.0
Name: pytest-single-file-logging
Version: 0.1.18
Summary: Allow for multiple processes to log to a single file
Home-page: https://github.com/darthghandi/pytest-single_file_logging
Author: Chris Saxey
Author-email: railesax@adobe.com
License: Apache Software License 2.0
Platform: UNKNOWN
Classifier: Development Status :: 4 - Beta
Classifier: Intended Audience :: Developers
Classifier: Topic :: Software Development :: Testing
Classifier: Programming Language :: Python
Classifier: Programming Language :: Python :: 2
Classifier: Programming Language :: Python :: 2.7
Classifier: Programming Language :: Python :: 3
Classifier: Programming Language :: Python :: 3.3
Classifier: Programming Language :: Python :: 3.4
Classifier: Programming Language :: Python :: 3.5
Classifier: Programming Language :: Python :: Implementation :: CPython
Classifier: Programming Language :: Python :: Implementation :: PyPy
Classifier: Operating System :: OS Independent
Classifier: License :: OSI Approved :: Apache Software License
Requires-Dist: gevent (>=1.1.0)
Requires-Dist: pytest (>=2.8.1)
